colliderml/__init__.py
colliderml/cli.py
colliderml/core/__init__.py
colliderml/core/get.py
colliderml/core/data/__init__.py
colliderml/core/data/config.py
colliderml/core/data/dataset.py
colliderml/core/data/manifest.py
colliderml/core/io/__init__.py
colliderml/core/io/downloader.py
colliderml/utils/__init__.py
colliderml-0.1.3.dist-info/LICENSE
colliderml-0.1.3.dist-info/METADATA
colliderml-0.1.3.dist-info/WHEEL
colliderml-0.1.3.dist-info/entry_points.txt
colliderml-0.1.3.dist-info/top_level.txt
colliderml-0.1.3.dist-info/RECORD
