Metadata-Version: 2.1
Name: colliderml
Version: 0.1.3
Summary: A modern machine learning library for high-energy physics data analysis
Home-page: https://github.com/murnanedaniel/colliderml
Author: Daniel Murnane
Author-email: dtmurnane@lbl.gov
License: UNKNOWN
Project-URL: Documentation, https://murnanedaniel.github.io/colliderml
Project-URL: Source, https://github.com/murnanedaniel/colliderml
Project-URL: Issues, https://github.com/murnanedaniel/colliderml/issues
Platform: UNKNOWN
Classifier: Development Status :: 3 - Alpha
Classifier: Intended Audience :: Science/Research
Classifier: License :: OSI Approved :: MIT License
Classifier: Programming Language :: Python :: 3.10
Classifier: Programming Language :: Python :: 3.11
Classifier: Topic :: Scientific/Engineering :: Physics
Requires-Python: >=3.10,<3.12
License-File: LICENSE
Requires-Dist: requests (>=2.31.0)
Requires-Dist: tqdm (>=4.66.0)
Requires-Dist: numpy (>=1.24.0)
Requires-Dist: pydantic (>=2.5.0)
Requires-Dist: h5py (>=3.10.0)
Provides-Extra: dev
Requires-Dist: pytest (>=7.4.0) ; extra == 'dev'
Requires-Dist: pytest-cov (>=4.1.0) ; extra == 'dev'
Requires-Dist: black (>=23.11.0) ; extra == 'dev'
Requires-Dist: ruff (>=0.1.6) ; extra == 'dev'
Requires-Dist: mypy (>=1.7.0) ; extra == 'dev'
Requires-Dist: mkdocs-material (>=9.4.0) ; extra == 'dev'
Requires-Dist: mkdocstrings[python] (>=0.24.0) ; extra == 'dev'
